bin/account-scout
bin/airdrop
bin/balance-account
bin/balance-wallet
bin/cancel-my-orders
bin/cancel-order
bin/close-token-account
bin/close-wrapped-sol-account
bin/crank-market
bin/delegate-account
bin/deposit
bin/download-trades
bin/ensure-account
bin/ensure-associated-token-account
bin/ensure-open-orders
bin/generate-keypair
bin/keeper
bin/log-subscribe
bin/mango-explorer-version
bin/market-buy
bin/market-sell
bin/marketmaker
bin/mint
bin/notify-below-minimum-sol-balance
bin/place-order
bin/redeem-mango
bin/redeem-pnl
bin/register-referrer-id
bin/report-transactions
bin/send-notification
bin/send-sols
bin/send-token
bin/set-discoverable-referrer
bin/settle-market
bin/show-account-balances
bin/show-account-dataframe
bin/show-account-info
bin/show-accounts
bin/show-address
bin/show-all-token-accounts
bin/show-delegated-accounts
bin/show-discoverable-referrer
bin/show-file
bin/show-funding-rates
bin/show-group
bin/show-group-prices
bin/show-interest-rates
bin/show-liquidity-mining-info
bin/show-market
bin/show-model-state
bin/show-my-orders
bin/show-open-orders
bin/show-orderbook
bin/show-price
bin/show-serum-open-orders
bin/show-token-balance
bin/show-transaction
bin/show-wrapped-sol
bin/simple-marketmaker
bin/unwrap-sol
bin/watch-address
bin/watch-minimum-balances
bin/who-am-i
bin/withdraw
bin/wrap-sol
data/.version
data/ids.json
data/mango_logs.json
data/nonspl.instrumentlist.devnet.json
data/nonspl.instrumentlist.json
data/overrides.tokenlist.devnet.json
data/overrides.tokenlist.json
data/solana.tokenlist.devnet.json
data/solana.tokenlist.json
mango/__init__.py
mango/account.py
mango/accountflags.py
mango/accountinfo.py
mango/accountinfoconverter.py
mango/accountscout.py
mango/addressableaccount.py
mango/arguments.py
mango/cache.py
mango/client.py
mango/combinableinstructions.py
mango/constants.py
mango/context.py
mango/contextbuilder.py
mango/datetimes.py
mango/encoding.py
mango/group.py
mango/healthcheck.py
mango/hedging/__init__.py
mango/hedging/hedger.py
mango_explorer-3.4.11.dist-info/LICENSE
mango_explorer-3.4.11.dist-info/WHEEL
mango_explorer-3.4.11.dist-info/METADATA
mango_explorer-3.4.11.dist-info/RECORD
